pyixx-0.1.0.dist-info/METADATA
pyixx-0.1.0.dist-info/WHEEL
pyixx/__init__.py
pyixx/__init__.pyi
pyixx/py.typed
pyixx/pyixx.cpython-313-x86_64-linux-gnu.so
pyixx-0.1.0.dist-info/RECORD
