Metadata-Version: 2.4
Name: pyixx
Version: 0.1.0
Classifier: Development Status :: 4 - Beta
Classifier: Programming Language :: Rust
Classifier: Programming Language :: Python :: Implementation :: CPython
Classifier: Programming Language :: Python :: 3.13
Classifier: License :: OSI Approved :: MIT License
Classifier: License :: OSI Approved :: Apache Software License
Summary: Python bindings for libixx - NüschtOS search index
Keywords: nix,nixos,search,index,nuschtos
Author-email: Félix Dorn <dorn@xfe.li>
License-Expression: MIT OR Apache-2.0
Requires-Python: >=3.13
Project-URL: Homepage, https://github.com/NuschtOS/ixx
Project-URL: Repository, https://github.com/felixdorn/mcp-nix
